parasol/__init__.py
parasol/compose.py
parasol/tokenize.py
parasol/resources/__init__.py
parasol/resources/composed/__init__.py
parasol/resources/composed/bpe.model
parasol/resources/composed/bpe.vocab
parasol/resources/decomposed/__init__.py
parasol/resources/decomposed/bpe.model
parasol/resources/decomposed/bpe.vocab
parasol_nlp-0.0.4.dist-info/LICENSE
parasol_nlp-0.0.4.dist-info/METADATA
parasol_nlp-0.0.4.dist-info/WHEEL
parasol_nlp-0.0.4.dist-info/top_level.txt
parasol_nlp-0.0.4.dist-info/RECORD
