Metadata-Version: 2.1
Name: parasol-nlp
Version: 0.0.4
Summary: Korean tokenizer with character decomposition
Home-page: UNKNOWN
Author: Keeho Ahn
Author-email: digsy89@gmail.com
License: UNKNOWN
Project-URL: Source, https://github.com/digsy89/parasol
Keywords: hangul korean nlp tokenizer
Platform: UNKNOWN
Classifier: Intended Audience :: Developers
Classifier: Programming Language :: Python :: 3
Classifier: License :: OSI Approved :: Apache Software License
Classifier: Operating System :: OS Independent
Classifier: Topic :: Text Processing
Requires-Python: >=3.6
Requires-Dist: hgtk
Requires-Dist: transitions
Requires-Dist: sentencepiece
Requires-Dist: importlib-resources
